django_ui/__init__.py
django_ui/admin.py
django_ui/apps.py
django_ui/forms.py
django_ui/models.py
django_ui/migrations/0001_initial.py
django_ui/migrations/__init__.py
django_ui/static/dynamic_field.js
django_ui/static/dynamic_field.min.js
django_ui/templates/admin/base_site.html
django_ui/templatetags/__init__.py
django_ui/templatetags/themeui_tag.py
django_ui-1.2.1.dist-info/LICENSE.txt
django_ui-1.2.1.dist-info/METADATA
django_ui-1.2.1.dist-info/WHEEL
django_ui-1.2.1.dist-info/top_level.txt
django_ui-1.2.1.dist-info/RECORD
