Metadata-Version: 2.1
Name: django-ui
Version: 1.2.1
Summary: Dynamic fields and settings theme color admin
Home-page: https://gitlab.com/florezjose/django_ui
Author: Jose Flórez (@rojosefo)
Author-email: florezjoserdolfo@gmail.com
License: MIT
Download-URL: https://gitlab.com/florezjose/django_ui/archive/1.2.1.tar.gz
Keywords: django,fields,dynamic,theme,color,checkbox,boolean,choices,chooser,admin,python
Platform: UNKNOWN
Classifier: Development Status :: 5 - Production/Stable
Classifier: Environment :: Web Environment
Classifier: Framework :: Django
Classifier: Framework :: Django :: 2.2
Classifier: Framework :: Django :: 3.1
Classifier: Intended Audience :: Developers
Classifier: License :: OSI Approved :: MIT License
Classifier: Natural Language :: English
Classifier: Operating System :: OS Independent
Classifier: Programming Language :: Python :: 3
Classifier: Programming Language :: Python :: 3.4
Classifier: Programming Language :: Python :: 3.5
Classifier: Programming Language :: Python :: 3.6
Classifier: Programming Language :: Python :: 3.7
Classifier: Programming Language :: Python :: 3.8
Classifier: Topic :: Software Development :: Build Tools
Requires: django(>=2.2)
Requires-Dist: Django (>=2.2)
